zheliku_tool/__about__.py
zheliku_tool/__init__.py
zheliku_tool/py.typed
zheliku_tool/tools/__init__.py
zheliku_tool/tools/time_tool/__init__.py
zheliku_tool/tools/time_tool/_helper.py
zheliku_tool/tools/time_tool/context.py
zheliku_tool/tools/time_tool/logger.py
zheliku_tool-0.1.5.dist-info/licenses/LICENSE
zheliku_tool-0.1.5.dist-info/METADATA
zheliku_tool-0.1.5.dist-info/WHEEL
zheliku_tool-0.1.5.dist-info/top_level.txt
zheliku_tool-0.1.5.dist-info/RECORD
