Metadata-Version: 2.4
Name: zheliku-tool
Version: 0.1.5
Summary: Lightweight timing decorator & context manager with loguru-like formatting, sync/async.
Author: zheliku
Project-URL: Homepage, https://github.com/zheliku/zheliku-tool
Project-URL: Issues, https://github.com/zheliku/zheliku-tool/issues
Project-URL: Repository, https://github.com/zheliku/zheliku-tool.git
Project-URL: Changelog, https://github.com/zheliku/zheliku-tool/master/CHANGELOG.md
Keywords: logging,timer,performance,decorator,asyncio
Requires-Python: >=3.12
License-File: LICENSE
Dynamic: license-file
